DePass/Net.py
DePass/__init__.py
DePass/analyze_utils.py
DePass/layer.py
DePass/model.py
DePass/utils.py
DePass-0.0.24.dist-info/LICENSE
DePass-0.0.24.dist-info/METADATA
DePass-0.0.24.dist-info/WHEEL
DePass-0.0.24.dist-info/top_level.txt
DePass-0.0.24.dist-info/RECORD
