Metadata-Version: 2.1
Name: DePass
Version: 0.0.24
Summary: DePass: a dual-enhanced graph learning framework for paired data integration
Requires-Python: >=3.8,<3.9
License-File: LICENSE
Requires-Dist: anndata>=0.9.2
Requires-Dist: hnswlib>=0.8.0
Requires-Dist: matplotlib<4.0.0,>=3.7.1
Requires-Dist: numpy<2.0.0,>=1.23.5
Requires-Dist: pandas<2.0.0,>=1.5.3
Requires-Dist: scanpy<2.0.0,>=1.9.8
Requires-Dist: scikit-learn<2.0.0,>=1.3.0
Requires-Dist: scipy<2.0.0,>=1.10.1
Requires-Dist: seaborn<0.14.0,>=0.12.2
Requires-Dist: tqdm<5.0.0,>=4.65.0
Requires-Dist: jupyter
